reactivedataflow/__init__.py
reactivedataflow/build_execution_graph.py
reactivedataflow/callbacks.py
reactivedataflow/conditions.py
reactivedataflow/config_provider.py
reactivedataflow/constants.py
reactivedataflow/decorators/__init__.py
reactivedataflow/decorators/apply_decorators.py
reactivedataflow/decorators/connect_input.py
reactivedataflow/decorators/connect_output.py
reactivedataflow/decorators/emit_conditions.py
reactivedataflow/decorators/fire_conditions.py
reactivedataflow/decorators/handle_async_output.py
reactivedataflow/decorators/verb.py
reactivedataflow/definitions.py
reactivedataflow/errors.py
reactivedataflow/execution_graph.py
reactivedataflow/graph_builder.py
reactivedataflow/model.py
reactivedataflow/nodes/__init__.py
reactivedataflow/nodes/definitions.py
reactivedataflow/nodes/input_node.py
reactivedataflow/nodes/io/__init__.py
reactivedataflow/nodes/io/emit_mode.py
reactivedataflow/nodes/io/input_mode.py
reactivedataflow/nodes/io/output_mode.py
reactivedataflow/nodes/io/verb_input.py
reactivedataflow/nodes/io/verb_output.py
reactivedataflow/nodes/node.py
reactivedataflow/nodes/verb_node.py
reactivedataflow/ports.py
reactivedataflow/py.typed
reactivedataflow/registry/__init__.py
reactivedataflow/registry/registration.py
reactivedataflow/registry/registry.py
reactivedataflow/registry/verb_constructor.py
reactivedataflow/utils/__init__.py
reactivedataflow/utils/equality.py
reactivedataflow-0.1.17.dist-info/METADATA
reactivedataflow-0.1.17.dist-info/WHEEL
reactivedataflow-0.1.17.dist-info/RECORD
