Metadata-Version: 2.1
Name: reactivedataflow
Version: 0.1.17
Summary: Reactive Dataflow Graphs
License: MIT
Author: Chris Trevino
Author-email: chtrevin@microsoft.com
Requires-Python: >=3.10,<4.0
Classifier: License :: OSI Approved :: MIT License
Classifier: Programming Language :: Python :: 3
Classifier: Programming Language :: Python :: 3.10
Classifier: Programming Language :: Python :: 3.11
Classifier: Programming Language :: Python :: 3.12
Requires-Dist: networkx (>=3.3,<4.0)
Requires-Dist: pydantic (>=2.7.4,<3.0.0)
Requires-Dist: reactivex (>=4.0.4,<5.0.0)
